{"nodes":[{"id":"d846666dfa8e7ab3","name":"Oscillator","data":{"baseFreq":8,"waveform":"sine"}},{"id":"38aad4ea1b0d88a6","name":"Gain","data":{"gain":0.5}},{"id":"4bc6e88cec5c0089","name":"Universal Output","data":{"gain":0.5}},{"id":"52eb245899d77a18","name":"Keyboard Note","data":{"octave":0,"halfstep":0,"waveform":"sawtooth","adsrProfile":{"attack":0.8,"attackLength":0.05,"decay":0.7,"decayLength":0.1,"sustain":0.001,"sustainLength":5,"releaseLength":1}}},{"id":"adc68036bfad583c","name":"Gain","data":{"gain":3}},{"id":"578694f1f533d971","name":"Biquad Filter","data":{"freq":700,"q":0.00001,"gain":1,"filterType":"lowpass"}},{"id":"dccbc20180e96ebb","name":"Keyboard Note","data":{"octave":-1,"halfstep":0,"waveform":"square","adsrProfile":{"attack":0.8,"attackLength":0.05,"decay":0.7,"decayLength":0.1,"sustain":0.001,"sustainLength":10,"releaseLength":1}}},{"id":"01198951f667698c","name":"Signal Flattener","data":{}},{"id":"26c5c7596748066e","name":"Bundle Debugger","data":{}},{"id":"4ba6c01722431d7e","name":"Bundle Debugger","data":{}},{"id":"e02f5d3d1f8b6689","name":"Noise","data":{"noiseType":"Brown Noise"}},{"id":"a5aeae4be4425a53","name":"Gain","data":{"gain":0.4}},{"id":"2de007ab073014df","name":"Biquad Filter","data":{"freq":500,"q":1,"gain":0,"filterType":"lowpass"}}],"connections":[{"source":"38aad4ea1b0d88a6","sourceOutput":"signal","target":"4bc6e88cec5c0089","targetInput":"signal"},{"source":"d846666dfa8e7ab3","sourceOutput":"signal","target":"adc68036bfad583c","targetInput":"signal"},{"source":"adc68036bfad583c","sourceOutput":"signal","target":"52eb245899d77a18","targetInput":"additionalFrequency"},{"source":"52eb245899d77a18","sourceOutput":"signal","target":"01198951f667698c","targetInput":"signal"},{"source":"01198951f667698c","sourceOutput":"signal","target":"578694f1f533d971","targetInput":"signal"},{"source":"adc68036bfad583c","sourceOutput":"signal","target":"dccbc20180e96ebb","targetInput":"additionalFrequency"},{"source":"dccbc20180e96ebb","sourceOutput":"signal","target":"26c5c7596748066e","targetInput":"signal"},{"source":"578694f1f533d971","sourceOutput":"signal","target":"4ba6c01722431d7e","targetInput":"signal"},{"source":"e02f5d3d1f8b6689","sourceOutput":"signal","target":"a5aeae4be4425a53","targetInput":"signal"},{"source":"a5aeae4be4425a53","sourceOutput":"signal","target":"2de007ab073014df","targetInput":"signal"},{"source":"2de007ab073014df","sourceOutput":"signal","target":"38aad4ea1b0d88a6","targetInput":"signal"},{"source":"578694f1f533d971","sourceOutput":"signal","target":"38aad4ea1b0d88a6","targetInput":"signal"},{"source":"dccbc20180e96ebb","sourceOutput":"signal","target":"01198951f667698c","targetInput":"signal"}]}